optimal/__init__.py
optimal/collections/__init__.py
optimal/collections/circular_queue.py
optimalpy-0.0.0.0.dist-info/LICENSE
optimalpy-0.0.0.0.dist-info/METADATA
optimalpy-0.0.0.0.dist-info/WHEEL
optimalpy-0.0.0.0.dist-info/entry_points.txt
optimalpy-0.0.0.0.dist-info/RECORD
