Metadata-Version: 2.1
Name: OptimalPy
Version: 0.0.0.0
Summary: Optimization capabilities.
License: Apache-2.0
Author: David Gayman
Author-email: drg.developer.2@gmail.com
Requires-Python: >=3.11,<4.0
Classifier: License :: OSI Approved :: Apache Software License
Classifier: Programming Language :: Python :: 3
Classifier: Programming Language :: Python :: 3.11
